AUTHORS.rst
CHANGELOG.rst
LICENSE
MANIFEST.in
README.rst
setup.py
autoload/__init__.py
autoload/grapher.py
autoload/reporter.py
autoload/tester.py
autoload.egg-info/PKG-INFO
autoload.egg-info/SOURCES.txt
autoload.egg-info/dependency_links.txt
autoload.egg-info/not-zip-safe
autoload.egg-info/requires.txt
autoload.egg-info/top_level.txt
autoload/bin/autoload
autoload/fonts/cicle.ttf
autoload/fonts/cicle_strong.ttf
autoload/media/logo.png